pclib/__init__.py
pclib/nn/__init__.py
pclib/nn/layers/__init__.py
pclib/nn/layers/conv.py
pclib/nn/layers/fc.py
pclib/nn/layers/fcatt.py
pclib/nn/models/FCPCN.py
pclib/nn/models/__init__.py
pclib/nn/models/conv_am.py
pclib/nn/models/conv_classifier.py
pclib/nn/models/conv_classifier_us.py
pclib/nn/models/fc_classifier.py
pclib/nn/models/fc_classifier_inv.py
pclib/nn/models/fc_classifier_us.py
pclib/nn/models/fc_classifier_us_inv.py
pclib/optim/__init__.py
pclib/optim/eval.py
pclib/optim/train.py
pclib/utils/__init__.py
pclib/utils/customdataset.py
pclib/utils/functional.py
pclib-2.0.0b2.dist-info/LICENSE
pclib-2.0.0b2.dist-info/METADATA
pclib-2.0.0b2.dist-info/WHEEL
pclib-2.0.0b2.dist-info/top_level.txt
pclib-2.0.0b2.dist-info/RECORD
