Metadata-Version: 2.1
Name: pclib
Version: 2.0.0b2
Summary: A torch-like package for building Predictive Coding Neural Networks.
Author: Joe Griffith
Author-email: joeagriffith@gmail.com
Keywords: python,neural networks,deep learning,predictive coding
Classifier: Development Status :: 4 - Beta
Classifier: Intended Audience :: Science/Research
Classifier: Programming Language :: Python :: 3
Classifier: Operating System :: Unix
Classifier: Operating System :: MacOS :: MacOS X
Classifier: Operating System :: Microsoft :: Windows
License-File: LICENSE
Requires-Dist: torch
Requires-Dist: torchvision
Requires-Dist: tqdm
Requires-Dist: matplotlib
